dreamberd/__init__.py
dreamberd/base.py
dreamberd/builtin.py
dreamberd/interpreter.py
dreamberd/serialize.py
dreamberd/processor/__init__.py
dreamberd/processor/expression_tree.py
dreamberd/processor/lexer.py
dreamberd/processor/syntax_tree.py
dreamberd_sigma-0.6.9.dist-info/LICENSE
dreamberd_sigma-0.6.9.dist-info/METADATA
dreamberd_sigma-0.6.9.dist-info/WHEEL
dreamberd_sigma-0.6.9.dist-info/entry_points.txt
dreamberd_sigma-0.6.9.dist-info/top_level.txt
dreamberd_sigma-0.6.9.dist-info/RECORD
