Metadata-Version: 2.1
Name: dreamberd-sigma
Version: 0.6.9
Summary: A customized fork of dreamberd interpreter
Home-page: https://github.com/skabdulhaq/dreamberd-interpreter
Author: AbdulHaq
Author-email: dev.abdulhaq@gmail.com
Classifier: Programming Language :: Python :: 3
Classifier: License :: OSI Approved :: MIT License
Classifier: Operating System :: OS Independent
Requires-Python: >=3.6
License-File: LICENSE
